setup.py
influxer2/__init__.py
influxer2/wsgi.py
influxer2.egg-info/PKG-INFO
influxer2.egg-info/SOURCES.txt
influxer2.egg-info/dependency_links.txt
influxer2.egg-info/requires.txt
influxer2.egg-info/top_level.txt