Metadata-Version: 1.0
Name: influxer2
Version: 0.0.2
Summary: A simple, fast uwsgi/gevent application to record pageview data to InfluxDB
Home-page: https://github.com/theonion/influxer2
Author: Vince Forgione
Author-email: vforgione@theonion.com
License: MIT
Keywords: uwsgi gevent influxdb pageview
Platform: UNKNOWN
